SmartSplit/__init__.py
SmartSplit/__main__.py
SmartSplit/cli.py
SmartSplit/core.py
SmartSplit/main.py
SmartSplit/examples/classname_labeling_example.py
SmartSplit/examples/dry_run_example.py
SmartSplit/examples/label_encoding_example.py
SmartSplit/utils/io.py
SmartSplit/utils/stats.py
build/lib/SmartSplit/__init__.py
build/lib/SmartSplit/__main__.py
build/lib/SmartSplit/cli.py
build/lib/SmartSplit/core.py
build/lib/SmartSplit/main.py
build/lib/SmartSplit/examples/classname_labeling_example.py
build/lib/SmartSplit/examples/dry_run_example.py
build/lib/SmartSplit/examples/label_encoding_example.py
build/lib/SmartSplit/utils/io.py
build/lib/SmartSplit/utils/stats.py
build/lib/build/lib/SmartSplit/__init__.py
build/lib/build/lib/SmartSplit/__main__.py
build/lib/build/lib/SmartSplit/cli.py
build/lib/build/lib/SmartSplit/core.py
build/lib/build/lib/SmartSplit/main.py
build/lib/build/lib/SmartSplit/examples/classname_labeling_example.py
build/lib/build/lib/SmartSplit/examples/dry_run_example.py
build/lib/build/lib/SmartSplit/examples/label_encoding_example.py
build/lib/build/lib/SmartSplit/utils/io.py
build/lib/build/lib/SmartSplit/utils/stats.py
smartspliter-1.0.7.dist-info/licenses/LICENSE
smartspliter-1.0.7.dist-info/METADATA
smartspliter-1.0.7.dist-info/WHEEL
smartspliter-1.0.7.dist-info/entry_points.txt
smartspliter-1.0.7.dist-info/top_level.txt
smartspliter-1.0.7.dist-info/RECORD
