Metadata-Version: 2.4
Name: SmartSpliter
Version: 1.0.7
Summary: A balanced dataset splitter for multi-domain, multi-class AI tasks.
Home-page: https://github.com/a1paka12/SmartSpliter
Author: alpaka
Author-email: alpaka <a1pakadeveloper@gmail.com>
Project-URL: Homepage, https://github.com/a1paka12/SmartSpliter
Project-URL: Repository, https://github.com/a1paka12/SmartSpliter
Classifier: Programming Language :: Python :: 3
Classifier: License :: OSI Approved :: MIT License
Classifier: Operating System :: OS Independent
Classifier: Topic :: Software Development :: Libraries :: Python Modules
Classifier: Topic :: Scientific/Engineering :: Artificial Intelligence
Classifier: Topic :: Utilities
Requires-Python: >=3.8
License-File: LICENSE
Requires-Dist: numpy
Requires-Dist: pandas
Requires-Dist: scikit-learn
Dynamic: author
Dynamic: home-page
Dynamic: license-file
Dynamic: requires-python
